django_tfactory/__init__.py
django_tfactory/tfactory.py
django_tfactory-0.1.3.dist-info/LICENSE
django_tfactory-0.1.3.dist-info/METADATA
django_tfactory-0.1.3.dist-info/WHEEL
django_tfactory-0.1.3.dist-info/entry_points.txt
django_tfactory-0.1.3.dist-info/top_level.txt
django_tfactory-0.1.3.dist-info/RECORD
