Metadata-Version: 2.1
Name: django-tfactory
Version: 0.1.3
Summary: A Django template factory
Home-page: https://github.com/SpiralDeveloper/django_tfactory
Author: Ashish Sahu
Author-email: spiraldeveloper@gmail.com
License: UNKNOWN
Platform: UNKNOWN
Classifier: Programming Language :: Python :: 3
Classifier: License :: OSI Approved :: MIT License
Classifier: Operating System :: OS Independent
Requires-Dist: beautifulsoup4
Requires-Dist: termcolor
